{
  "Name": "Heart",
  "Coordinates": [
    {
      "Name": "Heart1",
      "X": -801.177,
      "Y": -789.185,
      "Z": 20.3257
    },
    {
      "Name": "Heart2",
      "X": 679.187,
      "Y": -382.161,
      "Z": 19.1519
    },
    {
      "Name": "Heart3",
      "X": 171.703,
      "Y": 61.4919,
      "Z": 69.3713
    },
    {
      "Name": "Heart4",
      "X": -1071.59,
      "Y": -132.537,
      "Z": 17.4339
    },
    {
      "Name": "Heart5",
      "X": 233.43,
      "Y": -686.768,
      "Z": 28.9922
    }
  ]
}
