{
  "Name": "WP",
  "Coordinates": [
    {
      "Name": "",
      "X": -1692.21,
      "Y": 946.566,
      "Z": 87.2376
    },
    {
      "Name": "",
      "X": 279.811,
      "Y": -566.008,
      "Z": 96.26
    },
    {
      "Name": "",
      "X": 995.485,
      "Y": 64.0126,
      "Z": 175.067
    },
    {
      "Name": "",
      "X": -387.747,
      "Y": 406.267,
      "Z": 132.597
    },
    {
      "Name": "",
      "X": -1318.32,
      "Y": 534.179,
      "Z": 173.38
    },
    {
      "Name": "",
      "X": -702.513,
      "Y": -528.263,
      "Z": 143.428
    }
  ]
}
