{
  "Name": "POI",
  "Coordinates": [
    {
      "Name": "PoI1",
      "X": 31.1614,
      "Y": 1043.34,
      "Z": 145.471
    },
    {
      "Name": "PoI2",
      "X": 87.4852,
      "Y": 1227.44,
      "Z": 120.351
    },
    {
      "Name": "PoI3",
      "X": 249.493,
      "Y": 1064.07,
      "Z": 116.664
    },
    {
      "Name": "PoI4",
      "X": 337.437,
      "Y": 913.832,
      "Z": 112.496
    },
    {
      "Name": "PoI5",
      "X": -428.673,
      "Y": 933.896,
      "Z": 82.0992
    },
    {
      "Name": "PoI6",
      "X": -637.029,
      "Y": 946.497,
      "Z": 1.9287
    },
    {
      "Name": "PoI7",
      "X": -736.19,
      "Y": 1032.37,
      "Z": 80.0377
    },
    {
      "Name": "PoI8",
      "X": -512.911,
      "Y": 500.369,
      "Z": 84.0386
    },
    {
      "Name": "PoI9",
      "X": -111.991,
      "Y": 670.911,
      "Z": 95.8972
    },
    {
      "Name": "PoI10",
      "X": 96.3819,
      "Y": 553.334,
      "Z": 140.393
    },
    {
      "Name": "PoI11",
      "X": 724.689,
      "Y": 499.786,
      "Z": 35.2162
    },
    {
      "Name": "PoI12",
      "X": 722.959,
      "Y": 98.8035,
      "Z": 115.086
    },
    {
      "Name": "PoI13",
      "X": -450.835,
      "Y": 383.823,
      "Z": 75.3589
    },
    {
      "Name": "PoI14",
      "X": -636.947,
      "Y": 289.677,
      "Z": 64.3455
    },
    {
      "Name": "PoI15",
      "X": -748.219,
      "Y": 37.4248,
      "Z": 108.237
    },
    {
      "Name": "PoI16",
      "X": -539.974,
      "Y": 30.288,
      "Z": 99.2224
    },
    {
      "Name": "PoI17",
      "X": -712.19,
      "Y": -472.859,
      "Z": 114.558
    },
    {
      "Name": "PoI18",
      "X": -80.3517,
      "Y": -96.9256,
      "Z": 124.791
    },
    {
      "Name": "PoI19",
      "X": 1.48392,
      "Y": -198.55,
      "Z": 164.268
    },
    {
      "Name": "PoI20",
      "X": -380.76,
      "Y": -558.562,
      "Z": 135.223
    },
    {
      "Name": "PoI21",
      "X": -679.467,
      "Y": -1036.09,
      "Z": 45.4774
    },
    {
      "Name": "PoI22",
      "X": 1.35874,
      "Y": -727.599,
      "Z": 74.5497
    },
    {
      "Name": "PoI23",
      "X": 174.355,
      "Y": -540.826,
      "Z": 85.7916
    },
    {
      "Name": "PoI24",
      "X": 241.957,
      "Y": -898.69,
      "Z": 120.621
    }
  ]
}
