{
  "Name": "Kaineng fishing",
  "Coordinates": [
    {
      "Name": "fishing vendor",
      "X": -368.48,
      "Y": -304.51,
      "Z": 0.52
    },
    {
      "Name": "Channel fish",
      "X": 1247.97,
      "Y": 776.28,
      "Z": -1.29
    },
    {
      "Name": "Channel fish",
      "X": 1052.05,
      "Y": 430.89,
      "Z": -1.3
    },
    {
      "Name": "Channel fish",
      "X": 1177.68,
      "Y": 293.81,
      "Z": -1.3
    },
    {
      "Name": "Channel fish",
      "X": 1044.18,
      "Y": -26.88,
      "Z": -1.33
    },
    {
      "Name": "Channel fish",
      "X": 993.54,
      "Y": -45.91,
      "Z": -1.33
    },
    {
      "Name": "Channel fish",
      "X": 987.58,
      "Y": -47.69,
      "Z": 0.49
    },
    {
      "Name": "Channel fish",
      "X": 800.06,
      "Y": -285.34,
      "Z": -1.29
    },
    {
      "Name": "Channel fish",
      "X": 860.82,
      "Y": -410.74,
      "Z": -1.3
    },
    {
      "Name": "Channel fish",
      "X": 974.58,
      "Y": -472.94,
      "Z": -1.3
    },
    {
      "Name": "Channel fish",
      "X": 1063.82,
      "Y": -675.26,
      "Z": -1.29
    },
    {
      "Name": "Channel fish",
      "X": -79.49,
      "Y": -438.01,
      "Z": -1.29
    },
    {
      "Name": "Channel fish",
      "X": -413.69,
      "Y": -215.58,
      "Z": -1.29
    },
    {
      "Name": "Channel fish",
      "X": -369.17,
      "Y": -56.23,
      "Z": -1.32
    },
    {
      "Name": "Coastal fish",
      "X": -902.74,
      "Y": 642.47,
      "Z": -1.3
    },
    {
      "Name": "Coastal fish",
      "X": -1186.54,
      "Y": 577.63,
      "Z": -1.3
    },
    {
      "Name": "Coastal fish",
      "X": -1289.46,
      "Y": 442.54,
      "Z": -1.3
    },
    {
      "Name": "Coastal fish",
      "X": -1050.04,
      "Y": 366.53,
      "Z": -1.3
    },
    {
      "Name": "Coastal fish",
      "X": -1272.06,
      "Y": 39.21,
      "Z": -1.29
    },
    {
      "Name": "Coastal fish",
      "X": -1346.04,
      "Y": -161.21,
      "Z": -1.29
    },
    {
      "Name": "Coastal fish",
      "X": -1209.74,
      "Y": -229.86,
      "Z": -1.29
    },
    {
      "Name": "Coastal fish",
      "X": -1372.83,
      "Y": -378.9,
      "Z": -1.29
    },
    {
      "Name": "Coastal fish",
      "X": -1066.74,
      "Y": -323.86,
      "Z": -1.29
    },
    {
      "Name": "Coastal fish",
      "X": -1161.92,
      "Y": -467.36,
      "Z": -1.29
    },
    {
      "Name": "Coastal fish",
      "X": -1005.42,
      "Y": -502.49,
      "Z": -1.3
    },
    {
      "Name": "Coastal fish",
      "X": -1026.04,
      "Y": -685.61,
      "Z": -1.3
    },
    {
      "Name": "Coastal fish",
      "X": -678.23,
      "Y": -856.57,
      "Z": -1.3
    },
    {
      "Name": "Coastal fish",
      "X": -1359.6,
      "Y": -886.02,
      "Z": -1.3
    },
    {
      "Name": "channel fish",
      "X": -404.49,
      "Y": 33.06,
      "Z": -1.32
    },
    {
      "Name": "channel fish",
      "X": -365.61,
      "Y": 68.7,
      "Z": -1.32
    },
    {
      "Name": "channel fish",
      "X": -390.42,
      "Y": 167.67,
      "Z": -1.32
    },
    {
      "Name": "channel fish",
      "X": -475.26,
      "Y": 234.07,
      "Z": -1.32
    },
    {
      "Name": "channel fish",
      "X": -183.69,
      "Y": 218.85,
      "Z": -1.32
    },
    {
      "Name": "channel fish",
      "X": -168.54,
      "Y": 394.27,
      "Z": -1.28
    },
    {
      "Name": "channel fish",
      "X": 71.09,
      "Y": 656.37,
      "Z": -1.28
    },
    {
      "Name": "coastal fish",
      "X": -1403.88,
      "Y": 43.06,
      "Z": 1.07
    },
    {
      "Name": "coastal fish",
      "X": -1369.72,
      "Y": 157.9,
      "Z": 1.02
    },
    {
      "Name": "coastal fish",
      "X": -1144.27,
      "Y": -316.26,
      "Z": -1.3
    },
    {
      "Name": "coastal fish",
      "X": -1129.93,
      "Y": -383.82,
      "Z": 1.07
    },
    {
      "Name": "coastal fish",
      "X": -1309.32,
      "Y": -751.39,
      "Z": 0.48
    },
    {
      "Name": "channel fish",
      "X": -123.8,
      "Y": 375.36,
      "Z": -1.31
    }
  ]
}