{
  "Name": "Jahai Raptor Out Achievement-Story-Instance",
  "Coordinates": [
    {
      "Name": "1",
      "X": -101.49,
      "Y": -950.01,
      "Z": 108.2
    },
    {
      "Name": "2",
      "X": -97.52,
      "Y": -635.97,
      "Z": 103.65
    },
    {
      "Name": "3",
      "X": -84.08,
      "Y": -422.24,
      "Z": 105.43
    },
    {
      "Name": "4-pause-until-map-loads",
      "X": -76.23,
      "Y": -339.36,
      "Z": 116.12
    },
    {
      "Name": "5",
      "X": -68.95,
      "Y": -219.51,
      "Z": 112.7
    },
    {
      "Name": "6",
      "X": -56.41,
      "Y": -99.82,
      "Z": 117.65
    },
    {
      "Name": "7",
      "X": -49.75,
      "Y": 20.07,
      "Z": 120.85
    },
    {
      "Name": "8",
      "X": -46.06,
      "Y": 81.92,
      "Z": 119.53
    },
    {
      "Name": "9",
      "X": -36.99,
      "Y": 194.01,
      "Z": 116.78
    },
    {
      "Name": "10",
      "X": -220.18,
      "Y": 228.38,
      "Z": 119.69
    },
    {
      "Name": "11",
      "X": -304.36,
      "Y": 157.18,
      "Z": 115.74
    },
    {
      "Name": "12",
      "X": -418.61,
      "Y": 203.46,
      "Z": 122.04
    },
    {
      "Name": "13-pause-until-ma-loads",
      "X": -288.89,
      "Y": 675.41,
      "Z": 110.67
    },
    {
      "Name": "14",
      "X": -273.45,
      "Y": 783.79,
      "Z": 102.71
    },
    {
      "Name": "15",
      "X": -272.48,
      "Y": 911.34,
      "Z": 135.29
    },
    {
      "Name": "16",
      "X": -283.33,
      "Y": 1034.34,
      "Z": 164.73
    },
    {
      "Name": "17",
      "X": -294.64,
      "Y": 1289.59,
      "Z": 223.3
    },
    {
      "Name": "18",
      "X": 2.74,
      "Y": 1343.89,
      "Z": 225.85
    },
    {
      "Name": "19-just-jump-to-finish",
      "X": 362.99,
      "Y": 1426.27,
      "Z": 257.52
    }
  ]
}
