{
  "Name": "Path3-Butler",
  "Author": "Bloodmagicball",
  "Coordinates": [
    {
      "Name": "Start",
      "X": 117.616,
      "Y": 47.6551,
      "Z": 36.0056
    },
    {
      "Name": "killthem",
      "X": 28.3551,
      "Y": 70.0788,
      "Z": 22.3075
    },
    {
      "Name": "activate",
      "X": 116.474,
      "Y": 156.979,
      "Z": 27.7275
    },
    {
      "Name": "userifle",
      "X": 113.427,
      "Y": 147.796,
      "Z": 27.7406
    },
    {
      "Name": "killturrets-with-rifle",
      "X": 144.32,
      "Y": 191.073,
      "Z": 24.7531
    },
    {
      "Name": "kill-them",
      "X": 176.672,
      "Y": 271.151,
      "Z": 37.5494
    },
    {
      "Name": "endboss",
      "X": -266.257,
      "Y": 308.206,
      "Z": 16.6688
    }
  ]
}
