{
  "Name": "The-Rise-and-Fall-of-Kookoochoo",
  "Coordinates": [
    {
      "Name": "Kookoochoo-the-Insubstantial",
      "X": -176.04,
      "Y": 225.32,
      "Z": 128.42
    },
    {
      "Name": "Kookoochoo-the-Intolerant",
      "X": 76.25,
      "Y": 230.82,
      "Z": 1.43
    },
    {
      "Name": "Kookoochoo-the-Infallible",
      "X": 122.64,
      "Y": 278.74,
      "Z": 77.76
    },
    {
      "Name": "Kookoochoo-the-Inscrutable",
      "X": 182.78,
      "Y": 255.3,
      "Z": 61.62
    },
    {
      "Name": "Kookoochoo-the-Indubitable",
      "X": 76.21,
      "Y": 323.71,
      "Z": 55.84
    },
    {
      "Name": "talk-then-get-flyer-Incombustible",
      "X": -141.87,
      "Y": 239.12,
      "Z": 142.06
    },
    {
      "Name": "Kookoochoo-the-Inconsequential",
      "X": -93.38,
      "Y": 286.77,
      "Z": 144.31
    },
    {
      "Name": "Kookoochoo-the-Insecure",
      "X": -105.51,
      "Y": 294.09,
      "Z": 133.66
    },
    {
      "Name": "Kookoochoo-the-Inaccurate",
      "X": -146.51,
      "Y": 295.35,
      "Z": 123.31
    },
    {
      "Name": "Kookoochoo-the-Infirmed",
      "X": -217.13,
      "Y": 239.04,
      "Z": 109.5
    },
    {
      "Name": "Kookoochoo-the-Invalid",
      "X": -68.16,
      "Y": 157.63,
      "Z": 138.64
    },
    {
      "Name": "Kookoochoo-the-Infuriated",
      "X": -26.29,
      "Y": 109.92,
      "Z": 152.69
    },
    {
      "Name": "Kookoochoo-the-Indiscreet",
      "X": -17.53,
      "Y": 199.35,
      "Z": 140.69
    },
    {
      "Name": "Kookoochoo-the-Incautious",
      "X": -32.14,
      "Y": 107.37,
      "Z": 64.12
    },
    {
      "Name": "Kookoochoo-the-Infernal",
      "X": -113.05,
      "Y": 368.6,
      "Z": 122.22
    },
    {
      "Name": "Kookoochoo-the-Invidious",
      "X": -133.76,
      "Y": 327.26,
      "Z": 122.8
    },
    {
      "Name": "Kookoochoo-the-Inappropriate",
      "X": -77.24,
      "Y": 329.18,
      "Z": 103.9
    },
    {
      "Name": "Kookoochoo-the-Incoherent",
      "X": -65.33,
      "Y": 333.37,
      "Z": 76.43
    },
    {
      "Name": "Kookoochoo-the-Inane",
      "X": -30.99,
      "Y": 328.69,
      "Z": 68.86
    },
    {
      "Name": "Kookoochoo-the-Iniquitous",
      "X": -26.83,
      "Y": 325.6,
      "Z": 115.36
    },
    {
      "Name": "Kookoochoo-the-Inexplicable",
      "X": -5.68,
      "Y": 299.09,
      "Z": 93.61
    },
    {
      "Name": "Kookoochoo-the-Incongruous",
      "X": 39.13,
      "Y": 298.0,
      "Z": 94.89
    },
    {
      "Name": "Kookoochoo-the-Incomprehensible",
      "X": 127.34,
      "Y": 312.12,
      "Z": 97.76
    },
    {
      "Name": "Kookoochoo-the-Indisputable",
      "X": 126.27,
      "Y": 214.33,
      "Z": 72.89
    },
    {
      "Name": "Kookoochoo-the-Incontrovertible",
      "X": 143.64,
      "Y": 128.08,
      "Z": 53.54
    },
    {
      "Name": "Kookoochoo-the-Intemperate",
      "X": 37.82,
      "Y": 313.98,
      "Z": 10.4
    },
    {
      "Name": "Kookoochoo-the-Insane",
      "X": -43.23,
      "Y": 271.42,
      "Z": 2.5
    },
    {
      "Name": "Kookoochoo-the-Incriminated",
      "X": 36.95,
      "Y": 231.99,
      "Z": 1.55
    },
    {
      "Name": "Kookoochoo-the-Indicted",
      "X": -30.26,
      "Y": 234.55,
      "Z": 5.61
    },
    {
      "Name": "Kookoochoo-the-Incarcerated",
      "X": 13.16,
      "Y": 223.24,
      "Z": -21.39
    }
  ]
}
