{
  "Name": "Lost Lore of Desert Highlands",
  "Coordinates": [
    {
      "Name": "01",
      "X": 1538.07,
      "Y": 591.59,
      "Z": 225.62
    },
    {
      "Name": "02",
      "X": 574.19,
      "Y": 726.32,
      "Z": 355.49
    },
    {
      "Name": "03",
      "X": -594.42,
      "Y": -21.72,
      "Z": 343.48
    },
    {
      "Name": "04",
      "X": -212.64,
      "Y": -435.66,
      "Z": 305.76
    },
    {
      "Name": "05",
      "X": -863.49,
      "Y": -306.45,
      "Z": 238.99
    },
    {
      "Name": "06",
      "X": -1592.04,
      "Y": 385.3,
      "Z": 534.61
    },
    {
      "Name": "07",
      "X": -1525.17,
      "Y": 193.16,
      "Z": 341.44
    }
  ]
}