{
  "Name": "Hide And Seek",
  "Author": "RenSuhlo",
  "Coordinates": [
    {
      "Name": "Start",
      "X": 203.81,
      "Y": -135.36,
      "Z": 442.62
    },
    {
      "Name": "Spot 1",
      "X": 247.63,
      "Y": -177.54,
      "Z": 442.56
    },
    {
      "Name": "Spot 2",
      "X": 260.42,
      "Y": -269.26,
      "Z": 442.79
    },
    {
      "Name": "Spot 3",
      "X": 333.42,
      "Y": -197.48,
      "Z": 477.83
    },
    {
      "Name": "Spot 4",
      "X": 321.22,
      "Y": -144.38,
      "Z": 443.7
    },
    {
      "Name": "Spot 5",
      "X": 257.8,
      "Y": -52.92,
      "Z": 443.32
    },
    {
      "Name": "Spot 6",
      "X": 235.06,
      "Y": -36.79,
      "Z": 477.41
    },
    {
      "Name": "Spot 7",
      "X": 148.69,
      "Y": 15.02,
      "Z": 477.75
    },
    {
      "Name": "Spot 8",
      "X": 80.14,
      "Y": 30.72,
      "Z": 443.7
    },
    {
      "Name": "Spot 9",
      "X": -14.8,
      "Y": 28.4,
      "Z": 443.79
    },
    {
      "Name": "Spot 10",
      "X": 117.53,
      "Y": -103.21,
      "Z": 442.75
    }
  ]
}