{
  "Name": "POI",
  "Coordinates": [
    {
      "Name": "PoI1",
      "X": -44.8723,
      "Y": 186.192,
      "Z": 96.3852
    },
    {
      "Name": "PoI2",
      "X": 21.7873,
      "Y": 186.477,
      "Z": 27.1543
    },
    {
      "Name": "PoI3",
      "X": -131.377,
      "Y": 203.601,
      "Z": 36.5841
    },
    {
      "Name": "PoI4",
      "X": 42.7788,
      "Y": 39.0058,
      "Z": 83.4729
    },
    {
      "Name": "PoI5",
      "X": 33.7734,
      "Y": 73.2305,
      "Z": 127.256
    },
    {
      "Name": "PoI6",
      "X": 39.7421,
      "Y": 19.8548,
      "Z": 125.047
    },
    {
      "Name": "PoI7",
      "X": 140.228,
      "Y": 23.2505,
      "Z": 91.1784
    },
    {
      "Name": "PoI8",
      "X": 135.245,
      "Y": 69.7352,
      "Z": 89.2417
    },
    {
      "Name": "PoI9",
      "X": 180.98,
      "Y": 54.5545,
      "Z": 12.2073
    },
    {
      "Name": "PoI10",
      "X": 2.04188,
      "Y": -45.1485,
      "Z": 29.8679
    },
    {
      "Name": "PoI11",
      "X": -81.0051,
      "Y": -44.8844,
      "Z": 0.517299
    },
    {
      "Name": "PoI12",
      "X": 40.7007,
      "Y": -82.7425,
      "Z": 11.8383
    },
    {
      "Name": "PoI13",
      "X": 158.112,
      "Y": -105.871,
      "Z": 33.506
    },
    {
      "Name": "PoI14",
      "X": 70.4962,
      "Y": -90.4225,
      "Z": 51.3058
    },
    {
      "Name": "PoI15",
      "X": -73.7803,
      "Y": -29.3829,
      "Z": 54.189
    },
    {
      "Name": "PoI16",
      "X": -107.468,
      "Y": 46.1423,
      "Z": 58.2034
    },
    {
      "Name": "PoI17",
      "X": -120.904,
      "Y": 103.817,
      "Z": 60.5213
    },
    {
      "Name": "PoI18",
      "X": -113.439,
      "Y": 24.0941,
      "Z": 11.8231
    },
    {
      "Name": "PoI19",
      "X": 116.786,
      "Y": 103.206,
      "Z": 1.57148
    }
  ]
}
