{
  "Name": "Black Citadel",
  "Coordinates": [
    {
      "Name": "Vista1",
      "X": -170.553,
      "Y": -357.717,
      "Z": 85.8941
    },
    {
      "Name": "Vista2",
      "X": -51.7733,
      "Y": -65.7448,
      "Z": 125.094
    },
    {
      "Name": "Vista3",
      "X": 317.674,
      "Y": -29.2303,
      "Z": 217.698
    },
    {
      "Name": "Vista4",
      "X": -352.473,
      "Y": 119.957,
      "Z": 53.9408
    },
    {
      "Name": "Vista5",
      "X": 61.9819,
      "Y": 552.096,
      "Z": 197.062
    }
  ]
}
